<process draft="false" dev-studio-version="7.6.02.05">
  <process-def name=":AO-AD-VMware_VCloud:Utilities:VM_Management_Operations:Construct Item for Update VM Network Connection">
    <parameters>
      <input global="false" required="true">
        <from>vm id</from>
        <to>vm id</to>
      </input>
      <input global="false" required="true">
        <from>network name</from>
        <to>network name</to>
      </input>
      <input global="false" required="false">
        <from>ip address</from>
        <to>ip address</to>
      </input>
      <input global="false" required="false">
        <from>is connected</from>
        <to>is connected</to>
      </input>
      <input global="false" required="false">
        <from>mac address</from>
        <to>mac address</to>
      </input>
      <input global="false" required="false">
        <from>ip address allocation mode</from>
        <to>ip address allocation mode</to>
      </input>
      <input global="false" required="false">
        <from>primary network connection index</from>
        <to>primary network connection index</to>
      </input>
      <input global="false" required="false">
        <from>network connection index</from>
        <to>network connection index</to>
      </input>
      <output global="false" required="false">
        <to>items</to>
        <from>items</from>
      </output>
    </parameters>
    <access />
    <sequence>
      <assign>
        <assignment>
          <output>
            <to>items</to>
            <value>
              <empty />
            </value>
          </output>
          <xslt-stylesheet>
            <stylesheet-replacement-tokens>
              <replacement-token name="network name">
                <input global="false">
                  <from>network name</from>
                </input>
              </replacement-token>
              <replacement-token name="vm id">
                <input global="false">
                  <from>vm id</from>
                </input>
              </replacement-token>
              <replacement-token name="mac address">
                <input global="false">
                  <from>mac address</from>
                </input>
              </replacement-token>
              <replacement-token name="ip address allocation mode">
                <input global="false">
                  <from>ip address allocation mode</from>
                </input>
              </replacement-token>
              <replacement-token name="ip address">
                <input global="false">
                  <from>ip address</from>
                </input>
              </replacement-token>
              <replacement-token name="is connected">
                <input global="false">
                  <from>is connected</from>
                </input>
              </replacement-token>
              <replacement-token name="primary network connection index">
                <input global="false">
                  <from>primary network connection index</from>
                </input>
              </replacement-token>
              <replacement-token name="network connection index">
                <input global="false">
                  <from>network connection index</from>
                </input>
              </replacement-token>
            </stylesheet-replacement-tokens>
            <stylesheet><![CDATA[<xsl:stylesheet xmlns:xsl="http://www.w3.org/1999/XSL/Transform" version="1.0">
  <xsl:output indent="yes" />
  <xsl:template match="/">
    <items>
      <item>
        <parameters>
          <vm-id>${vm id}</vm-id>
          <network-connection-section>
            <primary-network-connection-index>${primary network connection index}</primary-network-connection-index>
            <network-connection>
              <network-connection-index>${network connection index}</network-connection-index>
              <network-name>${network name}</network-name>
              <ip-address>${ip address}</ip-address>
              <is-connected>${is connected}</is-connected>
              <mac-address>${mac address}</mac-address>
              <ip-address-allocation-mode>${ip address allocation mode}</ip-address-allocation-mode>
            </network-connection>
          </network-connection-section>
        </parameters>
      </item>
    </items>
  </xsl:template>
</xsl:stylesheet>]]></stylesheet>
          </xslt-stylesheet>
        </assignment>
        <meta>
          <documentation />
          <checkpoint>false</checkpoint>
        </meta>
        <location>:assign[1]</location>
      </assign>
    </sequence>
    <meta>
      <expose-to>
        <consumer>RULE</consumer>
        <consumer>SCHEDULE</consumer>
      </expose-to>
      <documentation>
        <description>Construct Item for Update VM Network Connection</description>
        <version></version>
      </documentation>
      <peer-location>
        <location>any</location>
      </peer-location>
      <record-metrics>false</record-metrics>
      <process-id>b62a6757-084f-4199-bea7-016425de7259</process-id>
      <author>admin</author>
      <category></category>
      <status></status>
      <keywords></keywords>
      <systems></systems>
      <last-modified-by>admin</last-modified-by>
      <last-modified>1354783415183</last-modified>
    </meta>
  </process-def>
</process>