<process draft="false" dev-studio-version="7.8.02">
  <process-def name=":BMC-SA-CLA_ITSM_Integration:Persistence:PagingSelectQuery">
    <parameters>
      <input global="false" required="true">
        <from>query</from>
        <to>query</to>
      </input>
      <input global="false" required="true">
        <from>numberOfRowsToOffset</from>
        <to>numberOfRowsToOffset</to>
      </input>
      <input global="false" required="true">
        <from>numberOfRowsToBeFetched</from>
        <to>numberOfRowsToBeFetched</to>
      </input>
      <output global="false" required="true">
        <to>adapter response</to>
        <from>adapter response</from>
      </output>
    </parameters>
    <access />
    <sequence>
      <assign>
        <assignment>
          <input global="true">
            <configuration>:BMC-SA-CLA_ITSM_Integration:Persistence:Default_SQL_Actor_Adapter</configuration>
          </input>
          <output>
            <to>sqlActorAdapter</to>
          </output>
        </assignment>
        <assignment>
          <input>
            <concat>
              <input required="false">
                <from>query</from>
              </input>
              <input>
                <value> offset </value>
              </input>
              <input required="false">
                <from>numberOfRowsToOffset</from>
              </input>
              <input>
                <value> rows fetch first </value>
              </input>
              <input required="false">
                <from>numberOfRowsToBeFetched</from>
              </input>
              <input>
                <value> rows only</value>
              </input>
            </concat>
          </input>
          <output>
            <to>pagingQuery</to>
          </output>
        </assignment>
        <meta>
          <documentation />
          <checkpoint>false</checkpoint>
        </meta>
        <after-execution>
          <log>
            <level>debug</level>
            <parameters>
              <input>
                <value>BMC-SA-CLA_ITSM_Integration:PagingSelectQuery=&gt;</value>
              </input>
              <input>
                <from>pagingQuery</from>
              </input>
            </parameters>
          </log>
        </after-execution>
        <location>:assign[1]</location>
      </assign>
      <call-process>
        <process-name>:AutoPilot-AD-Utilities:SQL:Ad Hoc Query</process-name>
        <parameters>
          <input>
            <from>sqlActorAdapter</from>
            <to>adapter name</to>
          </input>
          <input>
            <from>pagingQuery</from>
            <to>sql</to>
          </input>
          <input>
            <value></value>
            <to>user name</to>
          </input>
          <input>
            <value></value>
            <to>password</to>
          </input>
          <input>
            <value></value>
            <to>driver</to>
          </input>
          <input>
            <value></value>
            <to>url</to>
          </input>
          <output>
            <from>adapter response</from>
            <to>adapter response</to>
          </output>
        </parameters>
        <meta>
          <documentation />
          <run-mode-handling>
            <run-mode>OCP</run-mode>
            <allow-step-into>false</allow-step-into>
          </run-mode-handling>
          <checkpoint>false</checkpoint>
        </meta>
        <after-execution>
          <log>
            <level>debug</level>
            <parameters>
              <input>
                <value>BMC-SA-CLA_ITSM_Integration:PagingSelect Query Response=&gt;</value>
              </input>
              <input>
                <from>adapter response</from>
              </input>
            </parameters>
          </log>
        </after-execution>
        <location>:call-process[1]</location>
      </call-process>
    </sequence>
    <meta>
      <expose-to>
        <consumer>RULE</consumer>
        <consumer>SCHEDULE</consumer>
      </expose-to>
      <documentation>
        <description></description>
        <version></version>
      </documentation>
      <logging-options>
        <is-enabled>false</is-enabled>
        <log-file-name></log-file-name>
      </logging-options>
      <peer-location>
        <location>any</location>
      </peer-location>
      <record-metrics>false</record-metrics>
      <process-id>b3f68c59-bc61-44b8-aa3a-098d12a95a90</process-id>
      <author>AoAdmin</author>
      <category></category>
      <status></status>
      <keywords></keywords>
      <systems></systems>
      <last-modified-by>AoAdmin</last-modified-by>
      <last-modified>1467707075768</last-modified>
    </meta>
  </process-def>
</process>