<process draft="false" dev-studio-version="8.0.01">
  <process-def name=":AutoPilot-OA-ITSM_Automation:Change_Management:Do Search">
    <parameters>
      <input global="false" required="true">
        <description>Comma (,) separated list of Change IDs</description>
        <from>ChangeIDs</from>
        <to>ChangeIDs</to>
      </input>
      <input global="false" required="true">
        <description>Sample Value:

BMC_AR_System</description>
        <from>ITSMPlatform</from>
        <to>ITSMPlatform</to>
      </input>
      <input global="false" required="true">
        <description>Sample Value :
false</description>
        <from>RetrieveFailedCIs</from>
        <to>RetrieveFailedCIs</to>
      </input>
      <input global="false" required="true">
        <description>Sample Value: 
WebServiceAdapter</description>
        <from>AdapterName</from>
        <to>AdapterName</to>
      </input>
      <input global="false" required="true">
        <description>Sample Value :

http://&amp;lt;Midtier&amp;gt;:8080/arsys/services/ARService?server=&amp;lt;ARServer&amp;gt;&amp;amp;</description>
        <from>ServerURL</from>
        <to>ServerURL</to>
      </input>
      <input global="false" required="true">
        <description>Sample Value :

User</description>
        <from>UserName</from>
        <to>UserName</to>
      </input>
      <input global="false" required="true">
        <description>Sample Value :

Password</description>
        <from>Password</from>
        <to>Password</to>
      </input>
      <input global="false" required="true">
        <description>Sample Value:

CHG_ChangeOutboundInterface</description>
        <from>ChangeOutboundInterface</from>
        <to>ChangeOutboundInterface</to>
      </input>
      <input global="false" required="false">
        <from>Keystore</from>
        <to>Keystore</to>
      </input>
      <input global="false" required="false">
        <from>TrustStore</from>
        <to>TrustStore</to>
      </input>
      <input global="false" required="false">
        <from>Passphrase</from>
        <to>Passphrase</to>
      </input>
      <input global="false" required="false">
        <from>CommunicationProtocol</from>
        <to>CommunicationProtocol</to>
      </input>
      <input global="false" required="false">
        <description>XML, JSON (Default)</description>
        <from>ReturnDataFormat</from>
        <to>ReturnDataFormat</to>
      </input>
      <output global="false" required="false">
        <to>json response</to>
        <from>json response</from>
      </output>
      <output global="false" required="false">
        <to>xml response</to>
        <from>xml response</from>
      </output>
    </parameters>
    <access />
    <sequence>
      <switch>
        <meta>
          <documentation />
          <run-mode-handling>
            <run-mode>OCP</run-mode>
            <allow-step-into>true</allow-step-into>
          </run-mode-handling>
          <checkpoint>false</checkpoint>
        </meta>
        <execute-all-applicable-cases>false</execute-all-applicable-cases>
        <default>
          <sequence />
        </default>
        <case>
          <condition>
            <document>
              <input>
                <from>ITSMPlatform</from>
              </input>
            </document>
            <xpath-expression>
              <xpath-replacement-tokens />
              <xpath><![CDATA[normalize-space(.)]]></xpath>
            </xpath-expression>
            <xpath-expression>
              <xpath-replacement-tokens />
              <xpath><![CDATA[lower-case(.)]]></xpath>
            </xpath-expression>
            <xpath-expression>
              <xpath-replacement-tokens />
              <xpath><![CDATA[string(.) = "bmc_ar_system"]]></xpath>
            </xpath-expression>
          </condition>
          <sequence>
            <call-process>
              <process-name>:AutoPilot-OA-ITSM_Automation:Change_Management:Do Get Change Outbound Details</process-name>
              <parameters>
                <input>
                  <from>ChangeIDs</from>
                  <to>ChangeIDs</to>
                </input>
                <input>
                  <from>AdapterName</from>
                  <to>AdapterName</to>
                </input>
                <input>
                  <from>ServerURL</from>
                  <to>ServerURL</to>
                </input>
                <input>
                  <from>UserName</from>
                  <to>UserName</to>
                </input>
                <input>
                  <from>Password</from>
                  <to>Password</to>
                </input>
                <input>
                  <from>CommunicationProtocol</from>
                  <to>CommunicationProtocol</to>
                </input>
                <input>
                  <from>Keystore</from>
                  <to>Keystore</to>
                </input>
                <input>
                  <from>TrustStore</from>
                  <to>TrustStore</to>
                </input>
                <input>
                  <from>Passphrase</from>
                  <to>Passphrase</to>
                </input>
                <input>
                  <from>ChangeOutboundInterface</from>
                  <to>OutboundChangeInterface</to>
                </input>
                <output>
                  <from>ChangesXML</from>
                  <to>OutboundChangesXML</to>
                </output>
                <output>
                  <from>status</from>
                  <to>outbound status</to>
                </output>
                <output>
                  <from>error message</from>
                  <to>outbound error message</to>
                </output>
              </parameters>
              <meta>
                <documentation />
                <run-mode-handling>
                  <run-mode>OCP</run-mode>
                  <allow-step-into>false</allow-step-into>
                </run-mode-handling>
                <checkpoint>false</checkpoint>
              </meta>
              <location>:switch[1]:sequence[2]:call-process[1]</location>
            </call-process>
            <switch>
              <meta>
                <documentation />
                <run-mode-handling>
                  <run-mode>OCP</run-mode>
                  <allow-step-into>true</allow-step-into>
                </run-mode-handling>
                <checkpoint>false</checkpoint>
              </meta>
              <execute-all-applicable-cases>false</execute-all-applicable-cases>
              <default>
                <sequence>
                  <call-process>
                    <process-name>:AutoPilot-OA-ITSM_Automation:Utilities:Generate Response</process-name>
                    <parameters>
                      <input>
                        <value>failure</value>
                        <to>status</to>
                      </input>
                      <input>
                        <from>outbound error message</from>
                        <to>error message</to>
                      </input>
                      <input>
                        <value>Get Change Status</value>
                        <to>request type</to>
                      </input>
                      <input>
                        <from>outbound error message</from>
                        <to>data</to>
                      </input>
                      <output>
                        <from>json response</from>
                        <to>json response</to>
                      </output>
                    </parameters>
                    <meta>
                      <documentation />
                      <run-mode-handling>
                        <run-mode>OCP</run-mode>
                        <allow-step-into>false</allow-step-into>
                      </run-mode-handling>
                      <checkpoint>false</checkpoint>
                    </meta>
                    <location>:switch[1]:sequence[2]:switch[1]:sequence[1]:call-process[1]</location>
                  </call-process>
                </sequence>
              </default>
              <case>
                <condition>
                  <document>
                    <input>
                      <from>outbound status</from>
                    </input>
                  </document>
                  <xpath-expression>
                    <xpath-replacement-tokens />
                    <xpath><![CDATA[string(.) = "success"]]></xpath>
                  </xpath-expression>
                </condition>
                <sequence>
                  <switch>
                    <meta>
                      <documentation />
                      <run-mode-handling>
                        <run-mode>OCP</run-mode>
                        <allow-step-into>true</allow-step-into>
                      </run-mode-handling>
                      <checkpoint>false</checkpoint>
                    </meta>
                    <execute-all-applicable-cases>false</execute-all-applicable-cases>
                    <default>
                      <sequence>
                        <call-process>
                          <process-name>:AutoPilot-OA-ITSM_Automation:Utilities:Generate Response</process-name>
                          <parameters>
                            <input>
                              <value>success</value>
                              <to>status</to>
                            </input>
                            <input>
                              <concat>
                                <input required="false">
                                  <from>outbound error message</from>
                                </input>
                              </concat>
                              <to>error message</to>
                            </input>
                            <input>
                              <value>Get Change Status</value>
                              <to>request type</to>
                            </input>
                            <input>
                              <from>OutboundChangesXML</from>
                              <to>data</to>
                            </input>
                            <input>
                              <from>OutboundChangesXML</from>
                              <to>result count</to>
                              <xpath-expression>
                                <xpath-replacement-tokens />
                                <xpath><![CDATA[count(/changes/change)]]></xpath>
                              </xpath-expression>
                            </input>
                            <output>
                              <from>json response</from>
                              <to>json response</to>
                            </output>
                          </parameters>
                          <meta>
                            <documentation />
                            <run-mode-handling>
                              <run-mode>OCP</run-mode>
                              <allow-step-into>false</allow-step-into>
                            </run-mode-handling>
                            <checkpoint>false</checkpoint>
                          </meta>
                          <location>:switch[1]:sequence[2]:switch[1]:sequence[2]:switch[1]:sequence[1]:call-process[1]</location>
                        </call-process>
                      </sequence>
                    </default>
                    <case applies-if-any-condition-true="true">
                      <condition>
                        <document>
                          <input>
                            <from>RetrieveFailedCIs</from>
                          </input>
                        </document>
                        <xpath-expression>
                          <xpath-replacement-tokens />
                          <xpath><![CDATA[string(.) = "True"]]></xpath>
                        </xpath-expression>
                      </condition>
                      <condition>
                        <document>
                          <input>
                            <from>RetrieveFailedCIs</from>
                          </input>
                        </document>
                        <xpath-expression>
                          <xpath-replacement-tokens />
                          <xpath><![CDATA[string(.) = "true"]]></xpath>
                        </xpath-expression>
                      </condition>
                      <sequence>
                        <call-process>
                          <process-name>:AutoPilot-OA-ITSM_Automation:Change_Management:Do Get Change Transactional Details</process-name>
                          <parameters>
                            <input>
                              <from>ChangeIDs</from>
                              <to>ChangeIDs</to>
                            </input>
                            <input>
                              <from>AdapterName</from>
                              <to>AdapterName</to>
                            </input>
                            <input>
                              <from>ServerURL</from>
                              <to>ServerURL</to>
                            </input>
                            <input>
                              <from>UserName</from>
                              <to>UserName</to>
                            </input>
                            <input>
                              <from>Password</from>
                              <to>Password</to>
                            </input>
                            <input>
                              <from>CommunicationProtocol</from>
                              <to>CommunicationProtocol</to>
                            </input>
                            <input>
                              <from>Keystore</from>
                              <to>Keystore</to>
                            </input>
                            <input>
                              <from>TrustStore</from>
                              <to>TrustStore</to>
                            </input>
                            <input>
                              <from>Passphrase</from>
                              <to>Passphrase</to>
                            </input>
                            <input>
                              <from>ChangeOutboundInterface</from>
                              <to>outbound change interface</to>
                            </input>
                            <output>
                              <from>ChangesXML</from>
                              <to>TransactionalChangesXML</to>
                            </output>
                            <output>
                              <from>status</from>
                              <to>transactional status</to>
                            </output>
                            <output>
                              <from>error message</from>
                              <to>transactional error message</to>
                            </output>
                          </parameters>
                          <meta>
                            <documentation />
                            <run-mode-handling>
                              <run-mode>OCP</run-mode>
                              <allow-step-into>false</allow-step-into>
                            </run-mode-handling>
                            <checkpoint>false</checkpoint>
                          </meta>
                          <location>:switch[1]:sequence[2]:switch[1]:sequence[2]:switch[1]:sequence[2]:call-process[1]</location>
                        </call-process>
                        <switch>
                          <meta>
                            <documentation />
                            <run-mode-handling>
                              <run-mode>OCP</run-mode>
                              <allow-step-into>true</allow-step-into>
                            </run-mode-handling>
                            <checkpoint>false</checkpoint>
                          </meta>
                          <execute-all-applicable-cases>false</execute-all-applicable-cases>
                          <default>
                            <sequence>
                              <assign>
                                <meta>
                                  <documentation />
                                  <checkpoint>false</checkpoint>
                                </meta>
                                <before-execution>
                                  <log>
                                    <level>error</level>
                                    <parameters>
                                      <input>
                                        <value>Could not fetch the transactional details for change IDs: </value>
                                      </input>
                                      <input>
                                        <from>ChangeIDs</from>
                                      </input>
                                    </parameters>
                                  </log>
                                </before-execution>
                                <location>:switch[1]:sequence[2]:switch[1]:sequence[2]:switch[1]:sequence[2]:switch[1]:sequence[1]:assign[1]</location>
                              </assign>
                            </sequence>
                          </default>
                          <case>
                            <condition>
                              <document>
                                <input>
                                  <from>transactional status</from>
                                </input>
                              </document>
                              <xpath-expression>
                                <xpath-replacement-tokens />
                                <xpath><![CDATA[string(.) = "success"]]></xpath>
                              </xpath-expression>
                            </condition>
                            <sequence>
                              <call-process>
                                <process-name>:AutoPilot-OA-ITSM_Automation:Utilities:Merge Change XMLs</process-name>
                                <parameters>
                                  <input>
                                    <from>OutboundChangesXML</from>
                                    <to>ChangesOutboundXML</to>
                                  </input>
                                  <input>
                                    <from>TransactionalChangesXML</from>
                                    <to>ChangesTransactionalXML</to>
                                  </input>
                                  <output>
                                    <from>Changes</from>
                                    <to>Changes</to>
                                  </output>
                                </parameters>
                                <meta>
                                  <documentation />
                                  <run-mode-handling>
                                    <run-mode>OCP</run-mode>
                                    <allow-step-into>false</allow-step-into>
                                  </run-mode-handling>
                                  <checkpoint>false</checkpoint>
                                </meta>
                                <location>:switch[1]:sequence[2]:switch[1]:sequence[2]:switch[1]:sequence[2]:switch[1]:sequence[2]:call-process[1]</location>
                              </call-process>
                            </sequence>
                          </case>
                          <location>:switch[1]:sequence[2]:switch[1]:sequence[2]:switch[1]:sequence[2]:switch[1]</location>
                        </switch>
                        <call-process>
                          <process-name>:AutoPilot-OA-ITSM_Automation:Utilities:Generate Response</process-name>
                          <parameters>
                            <input>
                              <value>success</value>
                              <to>status</to>
                            </input>
                            <input>
                              <concat>
                                <input required="false">
                                  <from>transactional error message</from>
                                </input>
                              </concat>
                              <to>error message</to>
                            </input>
                            <input>
                              <value>Get Change Status</value>
                              <to>request type</to>
                            </input>
                            <input>
                              <from>Changes</from>
                              <to>data</to>
                              <xslt-stylesheet>
                                <stylesheet-replacement-tokens />
                                <stylesheet><![CDATA[<xsl:stylesheet xmlns:xsl="http://www.w3.org/1999/XSL/Transform" version="1.0">
  <xsl:output indent="no" />
  <xsl:template match="@*|node()">
    <xsl:copy>
      <xsl:apply-templates select="@*|node()" />
    </xsl:copy>
  </xsl:template>
  <xsl:template match="changes">
    <changes>
      <count>
        <xsl:value-of select="count(/changes/change)" disable-output-escaping="no" />
      </count>
      <xsl:apply-templates select="@*|node()" />
    </changes>
  </xsl:template>
</xsl:stylesheet>]]></stylesheet>
                              </xslt-stylesheet>
                            </input>
                            <input>
                              <from>Changes</from>
                              <to>result count</to>
                              <xpath-expression>
                                <xpath-replacement-tokens />
                                <xpath><![CDATA[count(/changes/change)]]></xpath>
                              </xpath-expression>
                            </input>
                            <output>
                              <from>json response</from>
                              <to>json response</to>
                            </output>
                          </parameters>
                          <meta>
                            <documentation />
                            <run-mode-handling>
                              <run-mode>OCP</run-mode>
                              <allow-step-into>false</allow-step-into>
                            </run-mode-handling>
                            <checkpoint>false</checkpoint>
                          </meta>
                          <location>:switch[1]:sequence[2]:switch[1]:sequence[2]:switch[1]:sequence[2]:call-process[2]</location>
                        </call-process>
                      </sequence>
                    </case>
                    <location>:switch[1]:sequence[2]:switch[1]:sequence[2]:switch[1]</location>
                  </switch>
                </sequence>
              </case>
              <location>:switch[1]:sequence[2]:switch[1]</location>
            </switch>
          </sequence>
        </case>
        <location>:switch[1]</location>
      </switch>
      <switch>
        <meta>
          <documentation />
          <run-mode-handling>
            <run-mode>OCP</run-mode>
            <allow-step-into>true</allow-step-into>
          </run-mode-handling>
          <checkpoint>false</checkpoint>
        </meta>
        <execute-all-applicable-cases>false</execute-all-applicable-cases>
        <default>
          <sequence />
        </default>
        <case>
          <condition>
            <document>
              <input>
                <from>ReturnDataFormat</from>
              </input>
            </document>
            <xpath-expression>
              <xpath-replacement-tokens />
              <xpath><![CDATA[.='XML' or .='xml']]></xpath>
            </xpath-expression>
          </condition>
          <sequence>
            <call-process>
              <process-name>:AutoPilot-OA-Common_Utilities:XML_Utilities:Convert JSON to XML</process-name>
              <parameters>
                <input>
                  <from>json response</from>
                  <to>JSON</to>
                </input>
                <output>
                  <from>XML</from>
                  <to>xml response</to>
                  <xslt-stylesheet>
                    <stylesheet-replacement-tokens />
                    <stylesheet><![CDATA[<xsl:stylesheet xmlns:xsl="http://www.w3.org/1999/XSL/Transform" version="1.0">
  <xsl:output indent="no" />
  <xsl:template match="/">
    <xsl:copy-of select="//bao-response" />
  </xsl:template>
</xsl:stylesheet>]]></stylesheet>
                  </xslt-stylesheet>
                </output>
              </parameters>
              <meta>
                <documentation />
                <run-mode-handling>
                  <run-mode>OCP</run-mode>
                  <allow-step-into>false</allow-step-into>
                </run-mode-handling>
                <checkpoint>false</checkpoint>
              </meta>
              <location>:switch[2]:sequence[2]:call-process[1]</location>
            </call-process>
          </sequence>
        </case>
        <location>:switch[2]</location>
      </switch>
    </sequence>
    <meta>
      <expose-to>
        <consumer>RULE</consumer>
        <consumer>SCHEDULE</consumer>
      </expose-to>
      <documentation>
        <description>Calls the Appropriate OA update operation depending on the input parameters.</description>
        <version></version>
      </documentation>
      <logging-options>
        <is-enabled>true</is-enabled>
        <log-file-name>Do-Update</log-file-name>
      </logging-options>
      <peer-location>
        <location>any</location>
      </peer-location>
      <record-metrics>true</record-metrics>
      <process-id>74a982d1-8b0b-4de3-a777-f8b068cbeada</process-id>
      <author>admin</author>
      <category></category>
      <status></status>
      <keywords></keywords>
      <systems></systems>
      <last-modified-by>aoadmin</last-modified-by>
      <last-modified>1526972638996</last-modified>
    </meta>
  </process-def>
</process>