<process draft="false" dev-studio-version="7.6.01.02">
  <process-def name=":AO-AD-IBM_Tivoli_Storage_Manager:Adapter_Action_Input_Constructors:v5.5:Schedule:Delete Association">
    <parameters>
      <input global="false" required="false">
        <description>The timeout value is seconds. This is the time after which the command will timeout regardless of whether the command execution is complete or not.</description>
        <from>timeout secs</from>
        <to>timeout secs</to>
      </input>
      <input global="false" required="true">
        <description>domain-name [Required] 
Specifies the name of the policy domain to which the schedule belongs. 
Valid values: The domain-name whom the associated schedule belongs to.
</description>
        <from>domain name</from>
        <to>domain name</to>
      </input>
      <input global="false" required="true">
        <description>
schedule-name [Required] 
Specifies the name of the schedule from which clients are to be disassociated.
Valid values: The schedule-name which is involved in the association.
 </description>
        <from>schedule name</from>
        <to>schedule name</to>
      </input>
      <input global="false" required="true">
        <description>
nodes-name [Required]: The node(s) associated with targeted association. Multiple nodes can be separated by commas with no intervening spaces.
Valid values: nodes’ name of the targeted association.

</description>
        <from>nodes name</from>
        <to>nodes name</to>
      </input>
      <output global="false" required="false">
        <to>items xml</to>
        <from>items xml</from>
      </output>
    </parameters>
    <access />
    <sequence>
      <assign>
        <assignment>
          <output>
            <to>items xml</to>
            <value>
              <root />
            </value>
          </output>
          <xslt-stylesheet>
            <stylesheet-replacement-tokens>
              <replacement-token name="timeout secs">
                <input global="false">
                  <from>timeout secs</from>
                </input>
              </replacement-token>
              <replacement-token name="domain name">
                <input global="false">
                  <from>domain name</from>
                </input>
              </replacement-token>
              <replacement-token name="schedule name">
                <input global="false">
                  <from>schedule name</from>
                </input>
              </replacement-token>
              <replacement-token name="nodes name">
                <input global="false">
                  <from>nodes name</from>
                </input>
              </replacement-token>
            </stylesheet-replacement-tokens>
            <stylesheet><![CDATA[<xsl:stylesheet xmlns:xsl="http://www.w3.org/1999/XSL/Transform" version="1.0">
  <xsl:output indent="no" />
  <xsl:template match="/">
    <items>
      <item>
        <operation-name>
          <xsl:text disable-output-escaping="no">delete-association</xsl:text>
        </operation-name>
        <timeout-secs>
          <xsl:value-of select="'${timeout secs}'" disable-output-escaping="no" />
        </timeout-secs>
        <command-options>
          <domain-name>
            <xsl:value-of select="'${domain name}'" disable-output-escaping="no" />
          </domain-name>
          <schedule-name>
            <xsl:value-of select="'${schedule name}'" disable-output-escaping="no" />
          </schedule-name>
          <nodes-name>
            <xsl:value-of select="'${nodes name}'" disable-output-escaping="no" />
          </nodes-name>
        </command-options>
      </item>
    </items>
  </xsl:template>
</xsl:stylesheet>]]></stylesheet>
          </xslt-stylesheet>
        </assignment>
        <meta>
          <documentation />
          <checkpoint>false</checkpoint>
        </meta>
        <after-execution>
          <log>
            <level>debug</level>
            <parameters>
              <input>
                <value>Items xml : </value>
              </input>
              <input>
                <from>items xml</from>
              </input>
            </parameters>
          </log>
        </after-execution>
        <location>:assign[1]</location>
      </assign>
    </sequence>
    <meta>
      <expose-to>
        <consumer>RULE</consumer>
        <consumer>SCHEDULE</consumer>
      </expose-to>
      <documentation>
        <description>This wrapper generates item xml for - delete association operations.</description>
        <version></version>
      </documentation>
      <peer-location>
        <location>any</location>
      </peer-location>
      <record-metrics>false</record-metrics>
      <process-id>abdb540f-524e-3e9d-acc6-429c795934cd</process-id>
      <author />
      <category />
      <status />
      <keywords />
      <systems />
      <last-modified-by />
      <last-modified>1290596966112</last-modified>
    </meta>
  </process-def>
</process>