<process draft="false" dev-studio-version="7.6.02.00">
  <process-def name=":AO-AD-Amazon_S3:Adapter_Actions:v1.0:Bucket_Operations:List Bucket Contents">
    <parameters>
      <input global="false" required="false">
        <description>adapter name    [Optional]
            The name of the adapter to use to handle the request. 

Default value: AmazonS3ActorAdapter</description>
        <from>adapter name</from>
        <to>adapter name</to>
      </input>
      <input global="false" required="false">
        <description>wsdl location [Optional]

The target WSDL URL for Amazon S3. The value of this parameter overrides the WSDL URL value provided in adapter configuration. A sample WSDL URL is - 
http://s3.amazonaws.com/doc/2006-03-01/AmazonS3.wsdl</description>
        <from>wsdl location</from>
        <to>wsdl location</to>
      </input>
      <input global="false" required="false">
        <description>endpoint address [Optional]

The WebService endpoint to use for performing operations on Amazon S3 buckets across different regions. Respective values for different regions are as below:

    * https://s3.amazonaws.com/soap — Endpoint located in the US Standard Region
    * https://s3-us-west-1.amazonaws.com/soap — Endpoint located in the US-West (Northern California) Region
    * https://s3-eu-west-1.amazonaws.com/soap ---Endpoint located in the EU (Ireland) Region
    * https://s3-ap-southeast-1.amazonaws.com/soap ---Endpoint located in the Asia Pacific (Singapore) Region
    * https://s3-ap-northeast-1.amazonaws.com/soap ---Endpoint located in the Asia Pacific (Tokyo) Region
</description>
        <from>endpoint address</from>
        <to>endpoint address</to>
      </input>
      <input global="false" required="false">
        <description>aws access key id [Optional]

The WebService access key is used to for identifying yourself as the sender of the request for the Amazon S3 operations. This key is provided by Amazon at the time of registration on Amazon S3 account.

Sample access key is is as follows:
1D9FVRAYCP1VJEXAMPLE=
</description>
        <from>aws access key id</from>
        <to>aws access key id</to>
      </input>
      <input global="false" required="false">
        <description>secret access key id [Optional]

Each access key has a secret key associated with it. Secret key is secret and should be known only by you and AWS. this is used only to calculate signatures to include in requestssent to AWS.</description>
        <from>secret access key</from>
        <to>secret access key</to>
      </input>
      <input global="false" required="true">
        <description>bucket [Mandatory]

Name of the bucket for which list is to be queried</description>
        <from>bucket</from>
        <to>bucket</to>
      </input>
      <input global="false" required="false">
        <description>prefix [Optional]

Limits the response to keys which begin with the indicated prefix</description>
        <from>prefix</from>
        <to>prefix</to>
      </input>
      <input global="false" required="false">
        <description>delimiter [Optional]

Type: xsd:String

Causes keys that contain the same string between the prefix and the first occurrence of the delimiter to be rolled up into a single result element in the CommonPrefixes collection</description>
        <from>delimiter</from>
        <to>delimiter</to>
      </input>
      <input global="false" required="false">
        <description>max keys [Optional]

The maximum number of keys you'd like to see in the response body</description>
        <from>max keys</from>
        <to>max keys</to>
      </input>
      <input global="false" required="false">
        <description>marker [Optional]

Indicates where in the bucket to begin listing</description>
        <from>marker</from>
        <to>marker</to>
      </input>
      <output global="false" required="false">
        <description>The adapter response containing the results. </description>
        <to>adapter response</to>
        <from>adapter response</from>
      </output>
    </parameters>
    <access />
    <sequence>
      <call-process>
        <process-name>:AO-AD-Amazon_S3:Utilities:Bucket_Operations:Construct Request for List Bucket Contents</process-name>
        <unique-id>0ea5f22b-a55c-34bb-ba9b-7534a2bd4247</unique-id>
        <parameters>
          <input>
            <from>wsdl location</from>
            <to>wsdl location</to>
          </input>
          <input>
            <from>endpoint address</from>
            <to>endpoint address</to>
          </input>
          <input>
            <from>aws access key id</from>
            <to>aws access key id</to>
          </input>
          <input>
            <from>secret access key</from>
            <to>secret access key</to>
          </input>
          <input>
            <from>bucket</from>
            <to>bucket</to>
          </input>
          <input>
            <from>prefix</from>
            <to>prefix</to>
          </input>
          <input>
            <from>delimiter</from>
            <to>delimiter</to>
          </input>
          <input>
            <from>max keys</from>
            <to>max keys</to>
          </input>
          <input>
            <from>marker</from>
            <to>marker</to>
          </input>
          <output>
            <from>adapter request</from>
            <to>adapter request</to>
          </output>
        </parameters>
        <meta>
          <documentation />
          <run-mode-handling>
            <run-mode>OCP</run-mode>
            <allow-step-into>false</allow-step-into>
          </run-mode-handling>
          <checkpoint>false</checkpoint>
        </meta>
        <after-execution>
          <console-output>
            <type>INFO</type>
            <summary>
              <concat>
                <input>
                  <value />
                </input>
              </concat>
            </summary>
            <detail>
              <concat>
                <input>
                  <value />
                </input>
              </concat>
            </detail>
          </console-output>
        </after-execution>
        <location>:call-process[1]</location>
      </call-process>
      <call-process>
        <process-name>:AO-AD-Amazon_S3:Utilities:Call Amazon S3 Adapter</process-name>
        <parameters>
          <input>
            <from>adapter name</from>
            <to>adapter name</to>
          </input>
          <input>
            <from>adapter request</from>
            <to>adapter request</to>
          </input>
          <output>
            <from>adapter response</from>
            <to>adapter response</to>
          </output>
        </parameters>
        <meta>
          <documentation />
          <run-mode-handling>
            <run-mode>OCP</run-mode>
            <allow-step-into>false</allow-step-into>
          </run-mode-handling>
          <checkpoint>false</checkpoint>
        </meta>
        <location>:call-process[2]</location>
      </call-process>
    </sequence>
    <meta>
      <expose-to>
        <consumer>RULE</consumer>
        <consumer>SCHEDULE</consumer>
      </expose-to>
      <documentation>
        <description>The ListBucket operation returns information about some of the items in the bucket depending on what input is passed as parameters.</description>
        <version>1.0</version>
      </documentation>
      <peer-location>
        <location>any</location>
      </peer-location>
      <record-metrics>false</record-metrics>
      <process-id>abb70c75-3945-342c-8498-c3e27a8b615d</process-id>
      <author />
      <category />
      <status />
      <keywords />
      <systems />
      <last-modified-by />
      <last-modified>1305018033470</last-modified>
    </meta>
  </process-def>
</process>