<process draft="false" dev-studio-version="7.6.03">
  <process-def name=":Closed_Loop_Compliance_ITSM_Integration:ITSM:Create Pre Approved Change">
    <parameters>
      <input global="false" required="false">
        <from>long description</from>
        <to>long description</to>
      </input>
      <input global="false" required="false">
        <from>short description</from>
        <to>short description</to>
      </input>
      <input global="false" required="false">
        <from>start date offset</from>
        <to>start date offset</to>
      </input>
      <input global="false" required="false">
        <from>maintanence window</from>
        <to>maintanence window</to>
      </input>
      <output global="false" required="false">
        <to>changes</to>
        <from>changes</from>
      </output>
      <output global="false" required="false">
        <to>success status</to>
        <from>success status</from>
      </output>
      <output global="false" required="false">
        <to>status message</to>
        <from>status message</from>
      </output>
    </parameters>
    <access />
    <sequence>
      <assign>
        <assignment>
          <output>
            <to>success status</to>
            <value>success</value>
          </output>
        </assignment>
        <meta>
          <documentation />
          <checkpoint>false</checkpoint>
        </meta>
        <location>:assign[1]</location>
      </assign>
      <call-process>
        <process-name>:Closed_Loop_Compliance_ITSM_Integration:Utilities:Extract Configuration Data</process-name>
        <parameters>
          <input>
            <value>ITSM</value>
            <to>configuration name</to>
          </input>
          <output>
            <from>incident platform</from>
            <to>incident platform</to>
          </output>
          <output>
            <from>incident template name</from>
            <to>incident template name</to>
          </output>
          <output>
            <from>change platform</from>
            <to>change platform</to>
          </output>
          <output>
            <from>change template name</from>
            <to>change template name</to>
          </output>
          <output>
            <from>task platform</from>
            <to>task platform</to>
          </output>
          <output>
            <from>authentication enable</from>
            <to>authentication enable</to>
          </output>
          <output>
            <from>authentication platform</from>
            <to>authentication platform</to>
          </output>
          <output>
            <from>authentication schema</from>
            <to>authentication schema</to>
          </output>
          <output>
            <from>authentication version</from>
            <to>authentication version</to>
          </output>
          <output>
            <from>authentication adapter</from>
            <to>authentication adapter</to>
          </output>
          <output>
            <from>authentication query mappings</from>
            <to>authentication query mappings</to>
          </output>
          <output>
            <from>authentication username</from>
            <to>authentication username</to>
          </output>
          <output>
            <from>success status</from>
            <to>success status</to>
          </output>
          <output>
            <from>status message</from>
            <to>status message</to>
          </output>
          <output>
            <from>configuration name</from>
            <to>configuration name</to>
          </output>
          <output>
            <from>incident default status</from>
            <to>incident default status</to>
          </output>
          <output>
            <from>incident default service type</from>
            <to>incident default service type</to>
          </output>
          <output>
            <from>incident default impact</from>
            <to>incident default impact</to>
          </output>
          <output>
            <from>incident default urgency</from>
            <to>incident default urgency</to>
          </output>
          <output>
            <from>change default status</from>
            <to>change default status</to>
          </output>
          <output>
            <from>change default change type</from>
            <to>change default change type</to>
          </output>
          <output>
            <from>change default impact</from>
            <to>change default impact</to>
          </output>
          <output>
            <from>change default urgency</from>
            <to>change default urgency</to>
          </output>
          <output>
            <from>change default risk level</from>
            <to>change default risk level</to>
          </output>
          <output>
            <from>change default timing</from>
            <to>change default timing</to>
          </output>
          <output>
            <from>incident default status reason</from>
            <to>incident default status reason</to>
          </output>
          <output>
            <from>incident default reported source</from>
            <to>incident default reported source</to>
          </output>
          <output>
            <from>configuration enable</from>
            <to>configuration enable</to>
          </output>
          <output>
            <from>configuration platform</from>
            <to>configuration platform</to>
          </output>
          <output>
            <from>configuration server class name</from>
            <to>configuration server class name</to>
          </output>
        </parameters>
        <meta>
          <documentation />
          <run-mode-handling>
            <run-mode>OCP</run-mode>
            <allow-step-into>false</allow-step-into>
          </run-mode-handling>
          <checkpoint>false</checkpoint>
        </meta>
        <location>:call-process[1]</location>
      </call-process>
      <call-process>
        <process-name>:Closed_Loop_Compliance_ITSM_Integration:ITSM:Query User Information</process-name>
        <parameters>
          <input>
            <from>change platform</from>
            <to>itsm platform</to>
          </input>
          <input>
            <from>configuration name</from>
            <to>configuration name</to>
          </input>
          <input>
            <from>authentication username</from>
            <to>user name</to>
          </input>
          <output>
            <from>login id</from>
            <to>login id</to>
          </output>
          <output>
            <from>first name</from>
            <to>first name</to>
          </output>
          <output>
            <from>last name</from>
            <to>last name</to>
          </output>
          <output>
            <from>company</from>
            <to>company</to>
          </output>
          <output>
            <from>company location</from>
            <to>company location</to>
          </output>
          <output>
            <from>success status</from>
            <to>success status</to>
          </output>
          <output>
            <from>status message</from>
            <to>status message</to>
          </output>
        </parameters>
        <meta>
          <documentation />
          <run-mode-handling>
            <run-mode>OCP</run-mode>
            <allow-step-into>false</allow-step-into>
          </run-mode-handling>
          <checkpoint>false</checkpoint>
        </meta>
        <location>:call-process[2]</location>
      </call-process>
      <switch>
        <meta>
          <documentation />
          <run-mode-handling>
            <run-mode>OCP</run-mode>
            <allow-step-into>true</allow-step-into>
          </run-mode-handling>
          <checkpoint>false</checkpoint>
        </meta>
        <execute-all-applicable-cases>false</execute-all-applicable-cases>
        <default>
          <sequence />
        </default>
        <case>
          <condition>
            <document>
              <input>
                <from>change platform</from>
              </input>
            </document>
            <xpath-expression>
              <xpath-replacement-tokens />
              <xpath><![CDATA[string(.)='BMC_AR_System']]></xpath>
            </xpath-expression>
          </condition>
          <sequence>
            <call-process>
              <process-name>:Closed_Loop_Compliance_ITSM_Integration:Remedy:Create Pre Approved Change</process-name>
              <parameters>
                <input>
                  <from>first name</from>
                  <to>first name</to>
                </input>
                <input>
                  <from>last name</from>
                  <to>last name</to>
                </input>
                <input>
                  <from>change default impact</from>
                  <to>change default impact</to>
                </input>
                <input>
                  <from>change default urgency</from>
                  <to>change default urgency</to>
                </input>
                <input>
                  <from>change default risk level</from>
                  <to>change default risk level</to>
                </input>
                <input>
                  <from>company</from>
                  <to>company</to>
                </input>
                <input>
                  <from>company location</from>
                  <to>company location</to>
                </input>
                <input>
                  <from>change default timing</from>
                  <to>change default timing</to>
                </input>
                <input>
                  <from>long description</from>
                  <to>long description</to>
                </input>
                <input>
                  <from>short description</from>
                  <to>short description</to>
                </input>
                <input>
                  <from>start date offset</from>
                  <to>start date offset</to>
                </input>
                <input>
                  <from>maintanence window</from>
                  <to>maintanence window</to>
                </input>
                <input>
                  <from>change template name</from>
                  <to>change template name</to>
                </input>
                <output>
                  <from>changes</from>
                  <to>changes</to>
                </output>
                <output>
                  <from>success status</from>
                  <to>success status</to>
                </output>
                <output>
                  <from>status message</from>
                  <to>status message</to>
                </output>
              </parameters>
              <meta>
                <documentation />
                <run-mode-handling>
                  <run-mode>OCP</run-mode>
                  <allow-step-into>false</allow-step-into>
                </run-mode-handling>
                <checkpoint>false</checkpoint>
              </meta>
              <location>:switch[1]:sequence[2]:call-process[1]</location>
            </call-process>
          </sequence>
        </case>
        <location>:switch[1]</location>
      </switch>
    </sequence>
    <meta>
      <expose-to>
        <consumer>RULE</consumer>
        <consumer>SCHEDULE</consumer>
      </expose-to>
      <documentation>
        <description></description>
        <version></version>
      </documentation>
      <peer-location>
        <location>any</location>
      </peer-location>
      <record-metrics>false</record-metrics>
      <process-id>3d3ca199-ed09-48eb-95d0-e673b20a0c39</process-id>
      <author>admin</author>
      <category></category>
      <status></status>
      <keywords></keywords>
      <systems></systems>
      <last-modified-by>admin</last-modified-by>
      <last-modified>1414569056372</last-modified>
    </meta>
  </process-def>
</process>